{
  "wav": "output\\ep_01\\EP01_VOICE_v200c.wav",
  "duration_sec": 1231.18,
  "sample_rate": 22050,
  "expected_boundaries_count": 5,
  "matched_count": 5,
  "expected_count_required": 5,
  "verdict": "PASS",
  "boundaries": [
    {
      "expected_sec": 153.75,
      "matched": true,
      "actual_duration_ms": 1519
    },
    {
      "expected_sec": 371.99,
      "matched": true,
      "actual_duration_ms": 1517
    },
    {
      "expected_sec": 511.3,
      "matched": true,
      "actual_duration_ms": 1518
    },
    {
      "expected_sec": 925.61,
      "matched": true,
      "actual_duration_ms": 1522
    },
    {
      "expected_sec": 1115.93,
      "matched": true,
      "actual_duration_ms": 1517
    }
  ]
}